[
  {},
  {
    "series_number": "30.01",
    "project": "Music",
    "series_title": "Federal Music Project",
    "description": "Little Symphony Orchestra--E. T. Fontana, Leader; Dance & Novelty Orchestra--E. Allessandra, Leader; Military Band--A. Ferroni, Leader; Dance & Novelty Orchestra--E. Ruffo, Leader; Negro Band--J. Martinez, Leader. Exterior.",
    "date_taken": "9/5/1936",
    "project_dates": "",
    "OP": "",
    "negatives": "6",
    "contact_prints": "0",
    "8x10_prints": "",
    "digital_photos": [
      "http://nutrias.org/~nopl/photos/wpa/images/30/300101.jpg",
      "http://nutrias.org/~nopl/photos/wpa/images/30/300102.jpg",
      "http://nutrias.org/~nopl/photos/wpa/images/30/300103.jpg",
      "http://nutrias.org/~nopl/photos/wpa/images/30/300105.jpg"
    ]
  },
  {
    "series_number": "30.02",
    "project": "Music",
    "series_title": "Federal Music Project",
    "description": "Community singing at Algiers. Interior. Damaged negatives.",
    "date_taken": "2/19/1937",
    "project_dates": "",
    "OP": "",
    "negatives": "2",
    "contact_prints": "2",
    "8x10_prints": "",
    "digital_photos": [
      "http://nutrias.org/~nopl/photos/wpa/images/30/300202.jpg"
    ]
  },
  {
    "series_number": "30.03",
    "project": "Music",
    "series_title": "Federal Music Project",
    "description": "[Orchestra in performance]. Interior.",
    "date_taken": "5/4/1937",
    "project_dates": "",
    "OP": "",
    "negatives": "5",
    "contact_prints": "5",
    "8x10_prints": "",
    "digital_photos": [
      "http://nutrias.org/~nopl/photos/wpa/images/30/300301.jpg",
      "http://nutrias.org/~nopl/photos/wpa/images/30/300302.jpg",
      "http://nutrias.org/~nopl/photos/wpa/images/30/300303.jpg",
      "http://nutrias.org/~nopl/photos/wpa/images/30/300305.jpg"
    ]
  },
  {
    "series_number": "30.04",
    "project": "Music",
    "series_title": "Federal Music Project",
    "description": "Community singing at Larkin's Playground, Algiers, and WPA band. Exterior.",
    "date_taken": "9/12/1937",
    "project_dates": "",
    "OP": "",
    "negatives": "6",
    "contact_prints": "0",
    "8x10_prints": "",
    "digital_photos": [
      "http://nutrias.org/~nopl/photos/wpa/images/30/300401.jpg",
      "http://nutrias.org/~nopl/photos/wpa/images/30/300402.jpg",
      "http://nutrias.org/~nopl/photos/wpa/images/30/300403.jpg",
      "http://nutrias.org/~nopl/photos/wpa/images/30/300404.jpg",
      "http://nutrias.org/~nopl/photos/wpa/images/30/300405.jpg",
      "http://nutrias.org/~nopl/photos/wpa/images/30/300406.jpg"
    ]
  },
  {
    "series_number": "30.05",
    "project": "Music",
    "series_title": "Federal Music Project",
    "description": "Negro Military Band in rehearsal. Interior.",
    "date_taken": "11/30/1937",
    "project_dates": "",
    "OP": "",
    "negatives": "4",
    "contact_prints": "4",
    "8x10_prints": "",
    "digital_photos": [
      "http://nutrias.org/~nopl/photos/wpa/images/30/300501.jpg",
      "http://nutrias.org/~nopl/photos/wpa/images/30/300502.jpg",
      "http://nutrias.org/~nopl/photos/wpa/images/30/300504.jpg"
    ]
  },
  {
    "series_number": "30.06",
    "project": "Music",
    "series_title": "Federal Music Project",
    "description": "WPA musicians playing at Rabouin Memorial School. Interior.",
    "date_taken": "2/23/1938",
    "project_dates": "",
    "OP": "",
    "negatives": "1",
    "contact_prints": "1",
    "8x10_prints": "",
    "digital_photos": [
      "http://nutrias.org/~nopl/photos/wpa/images/30/300601.jpg"
    ]
  },
  {
    "series_number": "30.07",
    "project": "Music",
    "series_title": "Federal Music Project",
    "description": "Harmonica class at Robert C. Davey School, 1307 Dryades Street. Jimmy Dillon, 14, 1621 Dryades; Rita Van Court, 13, 1824 Terpsichore; Gladys Luc, 13, 908 Howard; Anna Paladino, 15, 1400 Baronne. Interior.",
    "date_taken": "1/10/1940",
    "project_dates": "",
    "OP": "",
    "negatives": "1",
    "contact_prints": "0",
    "8x10_prints": "",
    "digital_photos": [
      "http://nutrias.org/~nopl/photos/wpa/images/30/300701.jpg"
    ]
  },
  {
    "series_number": "30.08",
    "project": "Music",
    "series_title": "Federal Music Project",
    "description": "Harmonica class at Robert C. Davey School, 1307 Dryades Street. General view of class with Inez Scroogs, 12, 1234 Carondelet as leader. Interior.",
    "date_taken": "1/10/1940",
    "project_dates": "",
    "OP": "",
    "negatives": "1",
    "contact_prints": "0",
    "8x10_prints": "",
    "digital_photos": [
      "http://nutrias.org/~nopl/photos/wpa/images/30/300802.jpg"
    ]
  },
  {
    "series_number": "30.09",
    "project": "Music",
    "series_title": "Federal Music Project",
    "description": "Harmonica class at Robert C. Davey School, 1307 Dryades Street. Gwynith Vead, 12, 1622 Thalia; Lucille Altobello, 13, 2009 Dryades; Lois Dorfer, 11, 1722 Baronne; Jennie Lazzara, 13, 1403 Dryades; Roy Laney, 12, 1319 Prytania; Cameron Brigham, 13, 1614 Thalia; Marvin Lemoine, 14, 1406 Carondelet; Alphonse Belletto, 12, 1610 S. Rampart; Inez Scroogs, 12, 1234 Carondelet (Leader). Interior.",
    "date_taken": "1/10/1940",
    "project_dates": "",
    "OP": "",
    "negatives": "1",
    "contact_prints": "0",
    "8x10_prints": "",
    "digital_photos": [
      "http://nutrias.org/~nopl/photos/wpa/images/30/300901.jpg"
    ]
  },
  {
    "series_number": "30.10",
    "project": "Music",
    "series_title": "Federal Music Project",
    "description": "Harmonica class at Robert C. Davey School, 1307 Dryades Street. Jacquelyn Oliver, 9, 1412 Terpsichore; Patricia Kelly, 11, 1712 Baronne; Richard Kelly, 13, 1712 Baronne. Interior.",
    "date_taken": "1/10/1940",
    "project_dates": "",
    "OP": "",
    "negatives": "1",
    "contact_prints": "1",
    "8x10_prints": "",
    "digital_photos": [
      "http://nutrias.org/~nopl/photos/wpa/images/30/301001.jpg"
    ]
  },
  {
    "series_number": "30.11",
    "project": "Music",
    "series_title": "Federal Music Project",
    "description": "Harmonica class at Poydras Home on Magazine Street. Audrey Beuche, 14; Norma Ferrer, 15; Annie Lyons, 15; Myrtle Hoover, 14; Ouida Cavignac, 15; Delories Blakemen, 15. Interior.",
    "date_taken": "1/10/1940",
    "project_dates": "",
    "OP": "",
    "negatives": "1",
    "contact_prints": "0",
    "8x10_prints": "",
    "digital_photos": [
      "http://nutrias.org/~nopl/photos/wpa/images/30/301101.jpg"
    ]
  },
  {
    "series_number": "30.12",
    "project": "Music",
    "series_title": "Federal Music Project",
    "description": "Harmonica class at Poydras Home on Magazine Street. General view of class. Interior.",
    "date_taken": "1/10/1940",
    "project_dates": "",
    "OP": "",
    "negatives": "1",
    "contact_prints": "0",
    "8x10_prints": "",
    "digital_photos": [
      "http://nutrias.org/~nopl/photos/wpa/images/30/301201.jpg"
    ]
  },
  {
    "series_number": "30.13",
    "project": "Music",
    "series_title": "Federal Music Project",
    "description": "Harmonica class at Home of Incurables. General view. Interior.",
    "date_taken": "1/10/1940",
    "project_dates": "",
    "OP": "",
    "negatives": "1",
    "contact_prints": "0",
    "8x10_prints": "",
    "digital_photos": [
      "http://nutrias.org/~nopl/photos/wpa/images/30/301301.jpg"
    ]
  },
  {
    "series_number": "30.14",
    "project": "Music",
    "series_title": "Federal Music Project",
    "description": "Harmonica class at Home of Incurables. Henry Hoffman and Delmar Hargrove. Interior.",
    "date_taken": "1/10/1940",
    "project_dates": "",
    "OP": "",
    "negatives": "1",
    "contact_prints": "0",
    "8x10_prints": "",
    "digital_photos": [
      "http://nutrias.org/~nopl/photos/wpa/images/30/301401.jpg"
    ]
  },
  {
    "series_number": "30.15",
    "project": "Music",
    "series_title": "Federal Music Project",
    "description": "Harmonica class at Home of Incurables. E. C. Heap; Billie and Pete Bourgeois (twins), 12. Interior.",
    "date_taken": "1/10/1940",
    "project_dates": "",
    "OP": "",
    "negatives": "2",
    "contact_prints": "0",
    "8x10_prints": "",
    "digital_photos": [
      "http://nutrias.org/~nopl/photos/wpa/images/30/301501.jpg"
    ]
  },
  {
    "series_number": "30.16",
    "project": "Music",
    "series_title": "Federal Music Project",
    "description": "Harmonica class at St. Elizabeth's Orphanage, Prytania Street and Napoleon Avenue. Mary Elizabeth McLaughlin, 13; Virginia Harris, 13; Hazel Bourgeois, 11. Sister Superior of St. Elizabeth's looks on as instructions take place. Interior.",
    "date_taken": "1/10/1940",
    "project_dates": "",
    "OP": "",
    "negatives": "1",
    "contact_prints": "0",
    "8x10_prints": "",
    "digital_photos": [
      "http://nutrias.org/~nopl/photos/wpa/images/30/301601.jpg"
    ]
  },
  {
    "series_number": "30.17",
    "project": "Music",
    "series_title": "Federal Music Project",
    "description": "WPA instructor employed on the Music Project teaches music to boys and girls at the St. Mark's Community Center. Interior.",
    "date_taken": "4/26/1940",
    "project_dates": "",
    "OP": "",
    "negatives": "5",
    "contact_prints": "5",
    "8x10_prints": "",
    "digital_photos": [
      "http://nutrias.org/~nopl/photos/wpa/images/30/301701.jpg",
      "http://nutrias.org/~nopl/photos/wpa/images/30/301702.jpg",
      "http://nutrias.org/~nopl/photos/wpa/images/30/301703.jpg"
    ]
  },
  {
    "series_number": "30.18",
    "project": "Music",
    "series_title": "Federal Music Project",
    "description": "WPA concert held at the Municipal Stadium in City Park. Exterior.",
    "date_taken": "7/24/1940",
    "project_dates": "",
    "OP": "",
    "negatives": "3",
    "contact_prints": "0",
    "8x10_prints": "",
    "digital_photos": [
      "http://nutrias.org/~nopl/photos/wpa/images/30/301802.jpg"
    ]
  },
  {
    "series_number": "30.19",
    "project": "Music",
    "series_title": "Federal Music Project",
    "description": "Noon-day concert held by the WPA band at Lafayette Square. Exterior.",
    "date_taken": "7/25/1940",
    "project_dates": "",
    "OP": "",
    "negatives": "3",
    "contact_prints": "0",
    "8x10_prints": "",
    "digital_photos": [
      "http://nutrias.org/~nopl/photos/wpa/images/30/301901.jpg",
      "http://nutrias.org/~nopl/photos/wpa/images/30/301902.jpg"
    ]
  },
  {
    "series_number": "30.20",
    "project": "Music",
    "series_title": "Federal Music Project",
    "description": "Training classes held for teachers on the WPA music project. Professor Klein, Miss Frances Deboll, assistant supervisor of the music project, Alcide Wallace, and Gladys W. Brooks. Interior.",
    "date_taken": "7/26/1940",
    "project_dates": "",
    "OP": "",
    "negatives": "1",
    "contact_prints": "0",
    "8x10_prints": "",
    "digital_photos": [
      "http://nutrias.org/~nopl/photos/wpa/images/30/302001.jpg"
    ]
  },
  {
    "series_number": "30.21",
    "project": "Music",
    "series_title": "Federal Music Project",
    "description": "Training classes held for teachers on the WPA music project. Professor Klein addressing the music supervisors. Interior.",
    "date_taken": "7/26/1940",
    "project_dates": "",
    "OP": "",
    "negatives": "2",
    "contact_prints": "0",
    "8x10_prints": "",
    "digital_photos": [
      "http://nutrias.org/~nopl/photos/wpa/images/30/302101.jpg"
    ]
  },
  {
    "series_number": "30.22",
    "project": "Music",
    "series_title": "Federal Music Project",
    "description": "Training classes held for teachers on the WPA music project. Mr. Maynard Klein, Newcomb, Director of Choral Activities and Professor of Public School Music, Miss Bertha Mumme, Mrs. Carrie E. Condrey, Emanuel Alessandra, and Merrill Solomon, WPA music teachers. Interior.",
    "date_taken": "7/26/1940",
    "project_dates": "",
    "OP": "",
    "negatives": "1",
    "contact_prints": "1",
    "8x10_prints": "",
    "digital_photos": [
      "http://nutrias.org/~nopl/photos/wpa/images/30/302201.jpg"
    ]
  },
  {
    "series_number": "30.23",
    "project": "Music",
    "series_title": "Federal Music Project",
    "description": "WPA Community Music Center at Royal Street and Almonaster Avenue. WPA music teachers instruct anyone who can not affort to pay for musical advantages.",
    "date_taken": "10/25/1940",
    "project_dates": "",
    "OP": "",
    "negatives": "9",
    "contact_prints": "9",
    "8x10_prints": "",
    "digital_photos": [
      "http://nutrias.org/~nopl/photos/wpa/images/30/302302.jpg",
      "http://nutrias.org/~nopl/photos/wpa/images/30/302303.jpg",
      "http://nutrias.org/~nopl/photos/wpa/images/30/302305.jpg",
      "http://nutrias.org/~nopl/photos/wpa/images/30/302306.jpg",
      "http://nutrias.org/~nopl/photos/wpa/images/30/302307.jpg",
      "http://nutrias.org/~nopl/photos/wpa/images/30/302308.jpg",
      "http://nutrias.org/~nopl/photos/wpa/images/30/302309.jpg"
    ]
  },
  {
    "series_number": "30.24",
    "project": "Music",
    "series_title": "Federal Music Project",
    "description": "WPA musicians hold a concert in honor of negro trainees who have been inducted into service. Exterior.",
    "date_taken": "4/30/1941",
    "project_dates": "",
    "OP": "",
    "negatives": "3",
    "contact_prints": "0",
    "8x10_prints": "",
    "digital_photos": [
      "http://nutrias.org/~nopl/photos/wpa/images/30/302401.jpg",
      "http://nutrias.org/~nopl/photos/wpa/images/30/302402.jpg",
      "http://nutrias.org/~nopl/photos/wpa/images/30/302403.jpg"
    ]
  },
  {
    "series_number": "30.25",
    "project": "Music",
    "series_title": "Federal Music Project",
    "description": "WPA conducted music classes at the Chinchuba Institute for the Deaf at Hope Haven, Louisiana. Interior.",
    "date_taken": "5/5/1941",
    "project_dates": "",
    "OP": "",
    "negatives": "7",
    "contact_prints": "0",
    "8x10_prints": "",
    "digital_photos": [
      "http://nutrias.org/~nopl/photos/wpa/images/30/302501.jpg",
      "http://nutrias.org/~nopl/photos/wpa/images/30/302502.jpg",
      "http://nutrias.org/~nopl/photos/wpa/images/30/302503.jpg",
      "http://nutrias.org/~nopl/photos/wpa/images/30/302505.jpg",
      "http://nutrias.org/~nopl/photos/wpa/images/30/302507.jpg"
    ]
  },
  {
    "series_number": "30.26",
    "project": "Music",
    "series_title": "Federal Music Project",
    "description": "WPA orchestra holds a concert of Inter-American music in the Sala Capitular of the Cabildo as a feature of the New Orleans celebration of the National Music Week. The Louisiana State Museum sponsored the concert and the Pan-American Consular Corps served as a reception committee. Interior.",
    "date_taken": "5/7/1941",
    "project_dates": "",
    "OP": "",
    "negatives": "8",
    "contact_prints": "0",
    "8x10_prints": "",
    "digital_photos": [
      "http://nutrias.org/~nopl/photos/wpa/images/30/302602.jpg",
      "http://nutrias.org/~nopl/photos/wpa/images/30/302603.jpg",
      "http://nutrias.org/~nopl/photos/wpa/images/30/302607.jpg",
      "http://nutrias.org/~nopl/photos/wpa/images/30/302608.jpg"
    ]
  },
  {
    "series_number": "30.27",
    "project": "Music",
    "series_title": "Federal Music Project",
    "description": "Regional conference of state music supervisors held in New Orleans to plan music instruction for enlisted men. Negatives 3 & 4: George Foster of Washington, deputy director of WPA music program; negatives 1 & 2: Mr. Rivers Randall of Oklahoma, acting chief of public activities program; Miss Christine McCann of Alabama, state music supervisor; Miss Sybil McDonal of Mississippi, assistant state musci supervisor; Mr. Rene Solomon of Louisiana, state music supervisor; Mrs. Merle Montgomery of Oklahoma, assist state music supervisor; Mr. Foster; Mrs. Jucille Lyon of Texas, state music supervisor; Mr. William Ralph Bennett of Mississippi, state music supervisor; Mr. Walter Dunham of Texas, assistant state music supervisor; Miss Exene Benefield of Arkansas, state music supervisor; Mr. Edward B. Moulton of Arkansas, chief of public activities program; Miss Frances L. Diboll of Louisiana, assistant state music supervisor.",
    "date_taken": "8/12/1941",
    "project_dates": "",
    "OP": "",
    "negatives": "4",
    "contact_prints": "0",
    "8x10_prints": "",
    "digital_photos": [
      "http://nutrias.org/~nopl/photos/wpa/images/30/302702.jpg",
      "http://nutrias.org/~nopl/photos/wpa/images/30/302704.jpg"
    ]
  }
]